[{"name":"__atuvs","value":"5feee1b3cf2772c1000","domain":"bannha888.com","path":"/","expires":1609492667,"size":26,"httpOnly":false,"secure":false,"session":false},{"name":"__atuvc","value":"1%7C0","domain":"bannha888.com","path":"/","expires":1643705267,"size":12,"httpOnly":false,"secure":false,"session":false},{"name":"_gid","value":"GA1.2.310684902.1609490866","domain":".bannha888.com","path":"/","expires":1609577268,"size":30,"httpOnly":false,"secure":false,"session":false},{"name":"cus","value":"1f379c7c5ca2044808660405e3f16a2f","domain":"bannha888.com","path":"/","expires":1641026865.675776,"size":35,"httpOnly":false,"secure":false,"session":false},{"name":"_gat_gtag_UA_141250758_1","value":"1","domain":".bannha888.com","path":"/","expires":1609490926,"size":25,"httpOnly":false,"secure":false,"session":false},{"name":"_ga","value":"GA1.2.1499160107.1609490866","domain":".bannha888.com","path":"/","expires":1672562868,"size":30,"httpOnly":false,"secure":false,"session":false},{"name":"PHPSESSID","value":"b1e5p5opqm7vk4b6466b3fh3f0","domain":"bannha888.com","path":"/","expires":-1,"size":35,"httpOnly":false,"secure":false,"session":true}]